{"elements":[{"from":[4.8571424,8.0,6.857143],"to":[17.428572,8.0,25.714287],"rotation":{"angle":0.0,"axis":"y","origin":[3.142857,0.0,6.857143]},"faces":{"east":{"uv":[8.5,4.9375,7.125,4.9375],"rotation":0,"texture":"#0","tintindex":0},"south":{"uv":[7.8125,4.875,7.125,4.875],"rotation":0,"texture":"#0","tintindex":0},"north":{"uv":[7.8125,4.75,7.125,4.75],"rotation":0,"texture":"#0","tintindex":0},"west":{"uv":[8.5,4.8125,7.125,4.8125],"rotation":0,"texture":"#0","tintindex":0},"up":{"uv":[2.125,11.4375,3.5,9.375],"rotation":0,"texture":"#0","tintindex":0},"down":{"uv":[2.125,9.375,3.5,11.4375],"rotation":0,"texture":"#0","tintindex":0}}}],"textures":{"0":"modelengine:entity/nocsy_rhino_beetle"},"display":{"head":{"translation":[0.0,-6.4,0.0],"scale":[4.0,4.0,4.0]}}}