{"elements":[{"from":[5.422857,7.9942856,5.422857],"to":[10.577143,13.148572,10.577143],"rotation":{"angle":0.0,"axis":"y","origin":[8.0,-7.4285717,8.0]},"faces":{"east":{"uv":[6.25,0.0,8.5,2.25],"rotation":0,"texture":"#0","tintindex":0},"south":{"uv":[6.75,2.25,9.0,4.5],"rotation":0,"texture":"#0","tintindex":0},"north":{"uv":[2.25,5.5,4.5,7.75],"rotation":0,"texture":"#0","tintindex":0},"west":{"uv":[4.5,6.75,6.75,9.0],"rotation":0,"texture":"#0","tintindex":0},"up":{"uv":[9.0,6.75,6.75,4.5],"rotation":0,"texture":"#0","tintindex":0},"down":{"uv":[9.0,6.75,6.75,9.0],"rotation":0,"texture":"#0","tintindex":0}}},{"from":[8.0,13.142858,6.0],"to":[8.0,17.142857,9.428572],"rotation":{"angle":45.0,"axis":"x","origin":[8.571428,13.142858,6.0]},"faces":{"east":{"uv":[3.0,9.5,1.5,11.25],"rotation":0,"texture":"#0","tintindex":0},"south":{"uv":[0.0,0.0,0.0,1.75],"rotation":0,"texture":"#0","tintindex":0},"north":{"uv":[0.0,0.0,0.0,1.75],"rotation":0,"texture":"#0","tintindex":0},"west":{"uv":[1.5,9.5,3.0,11.25],"rotation":0,"texture":"#0","tintindex":0},"up":{"uv":[0.0,1.5,0.0,0.0],"rotation":0,"texture":"#0","tintindex":0},"down":{"uv":[0.0,0.0,0.0,1.5],"rotation":0,"texture":"#0","tintindex":0}}},{"from":[6.285714,13.142858,6.5714283],"to":[6.285714,15.428572,8.285714],"rotation":{"angle":22.5,"axis":"x","origin":[8.571428,13.142858,6.5714283]},"faces":{"east":{"uv":[2.25,13.0,1.5,14.0],"rotation":0,"texture":"#0","tintindex":0},"south":{"uv":[0.0,0.0,0.0,1.0],"rotation":0,"texture":"#0","tintindex":0},"north":{"uv":[0.0,0.0,0.0,1.0],"rotation":0,"texture":"#0","tintindex":0},"west":{"uv":[1.5,13.0,2.25,14.0],"rotation":0,"texture":"#0","tintindex":0},"up":{"uv":[0.0,0.75,0.0,0.0],"rotation":0,"texture":"#0","tintindex":0},"down":{"uv":[0.0,0.0,0.0,0.75],"rotation":0,"texture":"#0","tintindex":0}}},{"from":[5.428571,9.142858,6.0],"to":[5.428571,14.285715,10.0],"rotation":{"angle":-22.5,"axis":"y","origin":[5.428571,9.142858,6.0]},"faces":{"east":{"uv":[9.0,3.5,10.75,5.75],"rotation":0,"texture":"#0","tintindex":0},"south":{"uv":[0.0,0.0,0.0,2.25],"rotation":0,"texture":"#0","tintindex":0},"north":{"uv":[0.0,0.0,0.0,2.25],"rotation":0,"texture":"#0","tintindex":0},"west":{"uv":[10.75,3.5,9.0,5.75],"rotation":0,"texture":"#0","tintindex":0},"up":{"uv":[0.0,1.75,0.0,0.0],"rotation":0,"texture":"#0","tintindex":0},"down":{"uv":[0.0,0.0,0.0,1.75],"rotation":0,"texture":"#0","tintindex":0}}},{"from":[5.142857,7.714286,5.142857],"to":[10.857143,13.428572,10.857143],"rotation":{"angle":0.0,"axis":"y","origin":[8.0,-7.4285717,8.0]},"faces":{"east":{"uv":[2.25,3.25,4.5,5.5],"rotation":0,"texture":"#0","tintindex":0},"south":{"uv":[4.0,0.0,6.25,2.25],"rotation":0,"texture":"#0","tintindex":0},"north":{"uv":[0.0,3.25,2.25,5.5],"rotation":0,"texture":"#0","tintindex":0},"west":{"uv":[4.5,2.25,6.75,4.5],"rotation":0,"texture":"#0","tintindex":0},"up":{"uv":[6.75,6.75,4.5,4.5],"rotation":0,"texture":"#0","tintindex":0},"down":{"uv":[2.25,5.5,0.0,7.75],"rotation":0,"texture":"#0","tintindex":0}}},{"from":[10.857143,13.428572,10.857143],"to":[5.142857,7.714286,5.142857],"rotation":{"angle":0.0,"axis":"y","origin":[8.0,-7.4285717,8.0]},"faces":{"east":{"uv":[15.75,15.25,16.0,14.75],"rotation":0,"texture":"#0","tintindex":0},"south":{"uv":[15.75,15.25,16.0,14.75],"rotation":0,"texture":"#0","tintindex":0},"north":{"uv":[15.75,15.25,16.0,14.75],"rotation":0,"texture":"#0","tintindex":0},"west":{"uv":[15.75,15.25,16.0,14.75],"rotation":0,"texture":"#0","tintindex":0},"up":{"uv":[14.375,15.8125,15.375,15.5],"rotation":0,"texture":"#0","tintindex":0},"down":{"uv":[15.75,15.0,16.0,14.75],"rotation":0,"texture":"#0","tintindex":0}}},{"from":[11.142858,12.0,7.714286],"to":[7.142857,8.571428,4.8571424],"rotation":{"angle":0.0,"axis":"y","origin":[8.0,-7.4285717,8.0]},"faces":{"east":{"uv":[15.75,14.75,16.0,14.5],"rotation":0,"texture":"#0","tintindex":0},"south":{"uv":[15.75,15.25,16.0,14.75],"rotation":0,"texture":"#0","tintindex":0},"north":{"uv":[15.75,14.75,16.0,14.5],"rotation":0,"texture":"#0","tintindex":0},"west":{"uv":[15.75,15.25,16.0,14.75],"rotation":0,"texture":"#0","tintindex":0},"up":{"uv":[15.75,14.75,16.0,14.5],"rotation":0,"texture":"#0","tintindex":0},"down":{"uv":[15.75,14.75,16.0,14.5],"rotation":0,"texture":"#0","tintindex":0}}},{"from":[8.857143,12.0,7.714286],"to":[4.8571424,8.571428,4.8571424],"rotation":{"angle":0.0,"axis":"y","origin":[8.0,-7.4285717,8.0]},"faces":{"east":{"uv":[16.0,15.25,15.75,14.75],"rotation":0,"texture":"#0","tintindex":0},"south":{"uv":[16.0,15.25,15.75,14.75],"rotation":0,"texture":"#0","tintindex":0},"north":{"uv":[16.0,14.75,15.75,14.5],"rotation":0,"texture":"#0","tintindex":0},"west":{"uv":[16.0,14.75,15.75,14.5],"rotation":0,"texture":"#0","tintindex":0},"up":{"uv":[16.0,14.75,15.75,14.5],"rotation":0,"texture":"#0","tintindex":0},"down":{"uv":[16.0,14.75,15.75,14.5],"rotation":0,"texture":"#0","tintindex":0}}},{"from":[8.142858,12.857143,5.714286],"to":[8.142858,17.428572,6.857143],"rotation":{"angle":45.0,"axis":"x","origin":[8.571428,13.142858,6.0]},"faces":{"east":{"uv":[15.75,14.5,16.0,14.75],"rotation":0,"texture":"#0","tintindex":0},"south":{"uv":[15.75,14.5,16.0,14.75],"rotation":0,"texture":"#0","tintindex":0},"north":{"uv":[15.75,14.5,16.0,14.75],"rotation":0,"texture":"#0","tintindex":0},"west":{"uv":[15.75,14.75,16.0,15.0],"rotation":0,"texture":"#0","tintindex":0},"up":{"uv":[15.75,14.5,16.0,14.75],"rotation":0,"texture":"#0","tintindex":0},"down":{"uv":[15.75,14.5,16.0,14.75],"rotation":0,"texture":"#0","tintindex":0}}},{"from":[8.142858,12.857143,6.857143],"to":[8.142858,16.285715,7.428571],"rotation":{"angle":45.0,"axis":"x","origin":[8.571428,13.142858,6.0]},"faces":{"east":{"uv":[15.75,14.5,16.0,14.75],"rotation":0,"texture":"#0","tintindex":0},"south":{"uv":[15.75,14.5,16.0,14.75],"rotation":0,"texture":"#0","tintindex":0},"north":{"uv":[15.75,14.5,16.0,14.75],"rotation":0,"texture":"#0","tintindex":0},"west":{"uv":[15.75,14.75,16.0,15.0],"rotation":0,"texture":"#0","tintindex":0},"up":{"uv":[15.75,14.5,16.0,14.75],"rotation":0,"texture":"#0","tintindex":0},"down":{"uv":[15.75,14.5,16.0,14.75],"rotation":0,"texture":"#0","tintindex":0}}},{"from":[8.142858,12.857143,8.0],"to":[8.142858,16.857143,9.142858],"rotation":{"angle":45.0,"axis":"x","origin":[8.571428,13.142858,6.0]},"faces":{"east":{"uv":[15.75,14.5,16.0,14.75],"rotation":0,"texture":"#0","tintindex":0},"south":{"uv":[15.75,14.5,16.0,14.75],"rotation":0,"texture":"#0","tintindex":0},"north":{"uv":[15.75,14.5,16.0,14.75],"rotation":0,"texture":"#0","tintindex":0},"west":{"uv":[15.75,14.75,16.0,15.0],"rotation":0,"texture":"#0","tintindex":0},"up":{"uv":[15.75,14.5,16.0,14.75],"rotation":0,"texture":"#0","tintindex":0},"down":{"uv":[15.75,14.5,16.0,14.75],"rotation":0,"texture":"#0","tintindex":0}}},{"from":[8.142858,12.857143,7.428571],"to":[8.142858,15.714286,8.0],"rotation":{"angle":45.0,"axis":"x","origin":[8.571428,13.142858,6.0]},"faces":{"east":{"uv":[15.75,14.5,16.0,14.75],"rotation":0,"texture":"#0","tintindex":0},"south":{"uv":[15.75,14.5,16.0,14.75],"rotation":0,"texture":"#0","tintindex":0},"north":{"uv":[15.75,14.5,16.0,14.75],"rotation":0,"texture":"#0","tintindex":0},"west":{"uv":[15.75,14.75,16.0,15.0],"rotation":0,"texture":"#0","tintindex":0},"up":{"uv":[15.75,14.5,16.0,14.75],"rotation":0,"texture":"#0","tintindex":0},"down":{"uv":[15.75,14.5,16.0,14.75],"rotation":0,"texture":"#0","tintindex":0}}},{"from":[8.142858,12.857143,9.142858],"to":[8.142858,15.142858,9.714286],"rotation":{"angle":45.0,"axis":"x","origin":[8.571428,13.142858,6.0]},"faces":{"east":{"uv":[15.75,14.5,16.0,14.75],"rotation":0,"texture":"#0","tintindex":0},"south":{"uv":[15.75,14.5,16.0,14.75],"rotation":0,"texture":"#0","tintindex":0},"north":{"uv":[15.75,14.5,16.0,14.75],"rotation":0,"texture":"#0","tintindex":0},"west":{"uv":[15.75,14.75,16.0,15.0],"rotation":0,"texture":"#0","tintindex":0},"up":{"uv":[15.75,14.5,16.0,14.75],"rotation":0,"texture":"#0","tintindex":0},"down":{"uv":[15.75,14.5,16.0,14.75],"rotation":0,"texture":"#0","tintindex":0}}},{"from":[7.857143,12.857143,9.142858],"to":[7.857143,15.142858,9.714286],"rotation":{"angle":45.0,"axis":"x","origin":[7.428571,13.142858,6.0]},"faces":{"east":{"uv":[16.0,14.75,15.75,15.0],"rotation":0,"texture":"#0","tintindex":0},"south":{"uv":[16.0,14.5,15.75,14.75],"rotation":0,"texture":"#0","tintindex":0},"north":{"uv":[16.0,14.5,15.75,14.75],"rotation":0,"texture":"#0","tintindex":0},"west":{"uv":[16.0,14.5,15.75,14.75],"rotation":0,"texture":"#0","tintindex":0},"up":{"uv":[16.0,14.5,15.75,14.75],"rotation":0,"texture":"#0","tintindex":0},"down":{"uv":[16.0,14.5,15.75,14.75],"rotation":0,"texture":"#0","tintindex":0}}},{"from":[7.857143,12.857143,7.428571],"to":[7.857143,15.714286,8.0],"rotation":{"angle":45.0,"axis":"x","origin":[7.428571,13.142858,6.0]},"faces":{"east":{"uv":[16.0,14.75,15.75,15.0],"rotation":0,"texture":"#0","tintindex":0},"south":{"uv":[16.0,14.5,15.75,14.75],"rotation":0,"texture":"#0","tintindex":0},"north":{"uv":[16.0,14.5,15.75,14.75],"rotation":0,"texture":"#0","tintindex":0},"west":{"uv":[16.0,14.5,15.75,14.75],"rotation":0,"texture":"#0","tintindex":0},"up":{"uv":[16.0,14.5,15.75,14.75],"rotation":0,"texture":"#0","tintindex":0},"down":{"uv":[16.0,14.5,15.75,14.75],"rotation":0,"texture":"#0","tintindex":0}}},{"from":[7.857143,12.857143,8.0],"to":[7.857143,16.857143,9.142858],"rotation":{"angle":45.0,"axis":"x","origin":[7.428571,13.142858,6.0]},"faces":{"east":{"uv":[16.0,14.75,15.75,15.0],"rotation":0,"texture":"#0","tintindex":0},"south":{"uv":[16.0,14.5,15.75,14.75],"rotation":0,"texture":"#0","tintindex":0},"north":{"uv":[16.0,14.5,15.75,14.75],"rotation":0,"texture":"#0","tintindex":0},"west":{"uv":[16.0,14.5,15.75,14.75],"rotation":0,"texture":"#0","tintindex":0},"up":{"uv":[16.0,14.5,15.75,14.75],"rotation":0,"texture":"#0","tintindex":0},"down":{"uv":[16.0,14.5,15.75,14.75],"rotation":0,"texture":"#0","tintindex":0}}},{"from":[7.857143,12.857143,6.857143],"to":[7.857143,16.285715,7.428571],"rotation":{"angle":45.0,"axis":"x","origin":[7.428571,13.142858,6.0]},"faces":{"east":{"uv":[16.0,14.75,15.75,15.0],"rotation":0,"texture":"#0","tintindex":0},"south":{"uv":[16.0,14.5,15.75,14.75],"rotation":0,"texture":"#0","tintindex":0},"north":{"uv":[16.0,14.5,15.75,14.75],"rotation":0,"texture":"#0","tintindex":0},"west":{"uv":[16.0,14.5,15.75,14.75],"rotation":0,"texture":"#0","tintindex":0},"up":{"uv":[16.0,14.5,15.75,14.75],"rotation":0,"texture":"#0","tintindex":0},"down":{"uv":[16.0,14.5,15.75,14.75],"rotation":0,"texture":"#0","tintindex":0}}},{"from":[7.857143,12.857143,5.714286],"to":[7.857143,17.428572,6.857143],"rotation":{"angle":45.0,"axis":"x","origin":[7.428571,13.142858,6.0]},"faces":{"east":{"uv":[16.0,14.75,15.75,15.0],"rotation":0,"texture":"#0","tintindex":0},"south":{"uv":[16.0,14.5,15.75,14.75],"rotation":0,"texture":"#0","tintindex":0},"north":{"uv":[16.0,14.5,15.75,14.75],"rotation":0,"texture":"#0","tintindex":0},"west":{"uv":[16.0,14.5,15.75,14.75],"rotation":0,"texture":"#0","tintindex":0},"up":{"uv":[16.0,14.5,15.75,14.75],"rotation":0,"texture":"#0","tintindex":0},"down":{"uv":[16.0,14.5,15.75,14.75],"rotation":0,"texture":"#0","tintindex":0}}},{"from":[6.428571,12.857143,6.285714],"to":[6.428571,15.714286,7.428571],"rotation":{"angle":22.5,"axis":"x","origin":[8.571428,13.142858,6.5714283]},"faces":{"east":{"uv":[15.75,14.5,16.0,14.75],"rotation":0,"texture":"#0","tintindex":0},"south":{"uv":[15.75,14.5,16.0,14.75],"rotation":0,"texture":"#0","tintindex":0},"north":{"uv":[15.75,14.5,16.0,14.75],"rotation":0,"texture":"#0","tintindex":0},"west":{"uv":[15.75,14.75,16.0,15.0],"rotation":0,"texture":"#0","tintindex":0},"up":{"uv":[15.75,14.5,16.0,14.75],"rotation":0,"texture":"#0","tintindex":0},"down":{"uv":[15.75,14.5,16.0,14.75],"rotation":0,"texture":"#0","tintindex":0}}},{"from":[6.428571,12.857143,7.428571],"to":[6.428571,15.142858,8.571428],"rotation":{"angle":22.5,"axis":"x","origin":[8.571428,13.142858,6.5714283]},"faces":{"east":{"uv":[15.75,14.5,16.0,14.75],"rotation":0,"texture":"#0","tintindex":0},"south":{"uv":[15.75,14.5,16.0,14.75],"rotation":0,"texture":"#0","tintindex":0},"north":{"uv":[15.75,14.5,16.0,14.75],"rotation":0,"texture":"#0","tintindex":0},"west":{"uv":[15.75,14.75,16.0,15.0],"rotation":0,"texture":"#0","tintindex":0},"up":{"uv":[15.75,14.5,16.0,14.75],"rotation":0,"texture":"#0","tintindex":0},"down":{"uv":[15.75,14.5,16.0,14.75],"rotation":0,"texture":"#0","tintindex":0}}},{"from":[6.142857,12.857143,6.285714],"to":[6.142857,15.714286,7.428571],"rotation":{"angle":22.5,"axis":"x","origin":[7.428571,13.142858,6.5714283]},"faces":{"east":{"uv":[16.0,14.75,15.75,15.0],"rotation":0,"texture":"#0","tintindex":0},"south":{"uv":[16.0,14.5,15.75,14.75],"rotation":0,"texture":"#0","tintindex":0},"north":{"uv":[16.0,14.5,15.75,14.75],"rotation":0,"texture":"#0","tintindex":0},"west":{"uv":[16.0,14.5,15.75,14.75],"rotation":0,"texture":"#0","tintindex":0},"up":{"uv":[16.0,14.5,15.75,14.75],"rotation":0,"texture":"#0","tintindex":0},"down":{"uv":[16.0,14.5,15.75,14.75],"rotation":0,"texture":"#0","tintindex":0}}},{"from":[6.142857,12.857143,7.428571],"to":[6.142857,15.142858,8.571428],"rotation":{"angle":22.5,"axis":"x","origin":[7.428571,13.142858,6.5714283]},"faces":{"east":{"uv":[16.0,14.75,15.75,15.0],"rotation":0,"texture":"#0","tintindex":0},"south":{"uv":[16.0,14.5,15.75,14.75],"rotation":0,"texture":"#0","tintindex":0},"north":{"uv":[16.0,14.5,15.75,14.75],"rotation":0,"texture":"#0","tintindex":0},"west":{"uv":[16.0,14.5,15.75,14.75],"rotation":0,"texture":"#0","tintindex":0},"up":{"uv":[16.0,14.5,15.75,14.75],"rotation":0,"texture":"#0","tintindex":0},"down":{"uv":[16.0,14.5,15.75,14.75],"rotation":0,"texture":"#0","tintindex":0}}},{"from":[5.485714,8.857143,6.285714],"to":[5.485714,12.285715,7.428571],"rotation":{"angle":-22.5,"axis":"y","origin":[5.428571,9.142858,6.0]},"faces":{"east":{"uv":[15.75,14.5,16.0,14.75],"rotation":0,"texture":"#0","tintindex":0},"south":{"uv":[15.75,14.5,16.0,14.75],"rotation":0,"texture":"#0","tintindex":0},"north":{"uv":[15.75,14.5,16.0,14.75],"rotation":0,"texture":"#0","tintindex":0},"west":{"uv":[15.75,14.75,16.0,15.0],"rotation":0,"texture":"#0","tintindex":0},"up":{"uv":[15.75,14.5,16.0,14.75],"rotation":0,"texture":"#0","tintindex":0},"down":{"uv":[15.75,14.5,16.0,14.75],"rotation":0,"texture":"#0","tintindex":0}}},{"from":[5.485714,9.428572,6.857143],"to":[5.485714,12.857143,8.0],"rotation":{"angle":-22.5,"axis":"y","origin":[5.428571,9.142858,6.0]},"faces":{"east":{"uv":[15.75,14.5,16.0,14.75],"rotation":0,"texture":"#0","tintindex":0},"south":{"uv":[15.75,14.5,16.0,14.75],"rotation":0,"texture":"#0","tintindex":0},"north":{"uv":[15.75,14.5,16.0,14.75],"rotation":0,"texture":"#0","tintindex":0},"west":{"uv":[15.75,14.75,16.0,15.0],"rotation":0,"texture":"#0","tintindex":0},"up":{"uv":[15.75,14.5,16.0,14.75],"rotation":0,"texture":"#0","tintindex":0},"down":{"uv":[15.75,14.5,16.0,14.75],"rotation":0,"texture":"#0","tintindex":0}}},{"from":[5.485714,10.571428,7.428571],"to":[5.485714,12.857143,8.571428],"rotation":{"angle":-22.5,"axis":"y","origin":[5.428571,9.142858,6.0]},"faces":{"east":{"uv":[15.75,14.5,16.0,14.75],"rotation":0,"texture":"#0","tintindex":0},"south":{"uv":[15.75,14.5,16.0,14.75],"rotation":0,"texture":"#0","tintindex":0},"north":{"uv":[15.75,14.5,16.0,14.75],"rotation":0,"texture":"#0","tintindex":0},"west":{"uv":[15.75,14.75,16.0,15.0],"rotation":0,"texture":"#0","tintindex":0},"up":{"uv":[15.75,14.5,16.0,14.75],"rotation":0,"texture":"#0","tintindex":0},"down":{"uv":[15.75,14.5,16.0,14.75],"rotation":0,"texture":"#0","tintindex":0}}},{"from":[5.485714,11.714286,8.571428],"to":[5.485714,14.0,9.714286],"rotation":{"angle":-22.5,"axis":"y","origin":[5.428571,9.142858,6.0]},"faces":{"east":{"uv":[15.75,14.5,16.0,14.75],"rotation":0,"texture":"#0","tintindex":0},"south":{"uv":[15.75,14.5,16.0,14.75],"rotation":0,"texture":"#0","tintindex":0},"north":{"uv":[15.75,14.5,16.0,14.75],"rotation":0,"texture":"#0","tintindex":0},"west":{"uv":[15.75,14.75,16.0,15.0],"rotation":0,"texture":"#0","tintindex":0},"up":{"uv":[15.75,14.5,16.0,14.75],"rotation":0,"texture":"#0","tintindex":0},"down":{"uv":[15.75,14.5,16.0,14.75],"rotation":0,"texture":"#0","tintindex":0}}},{"from":[5.485714,11.142858,8.0],"to":[5.485714,13.428572,9.142858],"rotation":{"angle":-22.5,"axis":"y","origin":[5.428571,9.142858,6.0]},"faces":{"east":{"uv":[15.75,14.5,16.0,14.75],"rotation":0,"texture":"#0","tintindex":0},"south":{"uv":[15.75,14.5,16.0,14.75],"rotation":0,"texture":"#0","tintindex":0},"north":{"uv":[15.75,14.5,16.0,14.75],"rotation":0,"texture":"#0","tintindex":0},"west":{"uv":[15.75,14.75,16.0,15.0],"rotation":0,"texture":"#0","tintindex":0},"up":{"uv":[15.75,14.5,16.0,14.75],"rotation":0,"texture":"#0","tintindex":0},"down":{"uv":[15.75,14.5,16.0,14.75],"rotation":0,"texture":"#0","tintindex":0}}},{"from":[5.485714,11.714286,9.142858],"to":[5.485714,14.571428,10.285714],"rotation":{"angle":-22.5,"axis":"y","origin":[5.428571,9.142858,6.0]},"faces":{"east":{"uv":[15.75,14.5,16.0,14.75],"rotation":0,"texture":"#0","tintindex":0},"south":{"uv":[15.75,14.5,16.0,14.75],"rotation":0,"texture":"#0","tintindex":0},"north":{"uv":[15.75,14.5,16.0,14.75],"rotation":0,"texture":"#0","tintindex":0},"west":{"uv":[15.75,14.75,16.0,15.0],"rotation":0,"texture":"#0","tintindex":0},"up":{"uv":[15.75,14.5,16.0,14.75],"rotation":0,"texture":"#0","tintindex":0},"down":{"uv":[15.75,14.5,16.0,14.75],"rotation":0,"texture":"#0","tintindex":0}}},{"from":[5.285714,11.714286,9.142858],"to":[5.285714,14.571428,10.285714],"rotation":{"angle":-22.5,"axis":"y","origin":[5.428571,9.142858,6.0]},"faces":{"east":{"uv":[15.75,14.75,16.0,15.0],"rotation":0,"texture":"#0","tintindex":0},"south":{"uv":[15.75,14.5,16.0,14.75],"rotation":0,"texture":"#0","tintindex":0},"north":{"uv":[15.75,14.5,16.0,14.75],"rotation":0,"texture":"#0","tintindex":0},"west":{"uv":[15.75,14.5,16.0,14.75],"rotation":0,"texture":"#0","tintindex":0},"up":{"uv":[15.75,14.5,16.0,14.75],"rotation":0,"texture":"#0","tintindex":0},"down":{"uv":[15.75,14.5,16.0,14.75],"rotation":0,"texture":"#0","tintindex":0}}},{"from":[5.285714,11.142858,8.0],"to":[5.285714,13.428572,9.142858],"rotation":{"angle":-22.5,"axis":"y","origin":[5.428571,9.142858,6.0]},"faces":{"east":{"uv":[15.75,14.75,16.0,15.0],"rotation":0,"texture":"#0","tintindex":0},"south":{"uv":[15.75,14.5,16.0,14.75],"rotation":0,"texture":"#0","tintindex":0},"north":{"uv":[15.75,14.5,16.0,14.75],"rotation":0,"texture":"#0","tintindex":0},"west":{"uv":[15.75,14.5,16.0,14.75],"rotation":0,"texture":"#0","tintindex":0},"up":{"uv":[15.75,14.5,16.0,14.75],"rotation":0,"texture":"#0","tintindex":0},"down":{"uv":[15.75,14.5,16.0,14.75],"rotation":0,"texture":"#0","tintindex":0}}},{"from":[5.285714,11.714286,8.571428],"to":[5.285714,14.0,9.714286],"rotation":{"angle":-22.5,"axis":"y","origin":[5.428571,9.142858,6.0]},"faces":{"east":{"uv":[15.75,14.75,16.0,15.0],"rotation":0,"texture":"#0","tintindex":0},"south":{"uv":[15.75,14.5,16.0,14.75],"rotation":0,"texture":"#0","tintindex":0},"north":{"uv":[15.75,14.5,16.0,14.75],"rotation":0,"texture":"#0","tintindex":0},"west":{"uv":[15.75,14.5,16.0,14.75],"rotation":0,"texture":"#0","tintindex":0},"up":{"uv":[15.75,14.5,16.0,14.75],"rotation":0,"texture":"#0","tintindex":0},"down":{"uv":[15.75,14.5,16.0,14.75],"rotation":0,"texture":"#0","tintindex":0}}},{"from":[5.285714,10.571428,7.428571],"to":[5.285714,12.857143,8.571428],"rotation":{"angle":-22.5,"axis":"y","origin":[5.428571,9.142858,6.0]},"faces":{"east":{"uv":[15.75,14.75,16.0,15.0],"rotation":0,"texture":"#0","tintindex":0},"south":{"uv":[15.75,14.5,16.0,14.75],"rotation":0,"texture":"#0","tintindex":0},"north":{"uv":[15.75,14.5,16.0,14.75],"rotation":0,"texture":"#0","tintindex":0},"west":{"uv":[15.75,14.5,16.0,14.75],"rotation":0,"texture":"#0","tintindex":0},"up":{"uv":[15.75,14.5,16.0,14.75],"rotation":0,"texture":"#0","tintindex":0},"down":{"uv":[15.75,14.5,16.0,14.75],"rotation":0,"texture":"#0","tintindex":0}}},{"from":[5.285714,9.428572,6.857143],"to":[5.285714,12.857143,8.0],"rotation":{"angle":-22.5,"axis":"y","origin":[5.428571,9.142858,6.0]},"faces":{"east":{"uv":[15.75,14.75,16.0,15.0],"rotation":0,"texture":"#0","tintindex":0},"south":{"uv":[15.75,14.5,16.0,14.75],"rotation":0,"texture":"#0","tintindex":0},"north":{"uv":[15.75,14.5,16.0,14.75],"rotation":0,"texture":"#0","tintindex":0},"west":{"uv":[15.75,14.5,16.0,14.75],"rotation":0,"texture":"#0","tintindex":0},"up":{"uv":[15.75,14.5,16.0,14.75],"rotation":0,"texture":"#0","tintindex":0},"down":{"uv":[15.75,14.5,16.0,14.75],"rotation":0,"texture":"#0","tintindex":0}}},{"from":[5.285714,8.857143,6.285714],"to":[5.285714,12.285715,7.428571],"rotation":{"angle":-22.5,"axis":"y","origin":[5.428571,9.142858,6.0]},"faces":{"east":{"uv":[15.75,14.75,16.0,15.0],"rotation":0,"texture":"#0","tintindex":0},"south":{"uv":[15.75,14.5,16.0,14.75],"rotation":0,"texture":"#0","tintindex":0},"north":{"uv":[15.75,14.5,16.0,14.75],"rotation":0,"texture":"#0","tintindex":0},"west":{"uv":[15.75,14.5,16.0,14.75],"rotation":0,"texture":"#0","tintindex":0},"up":{"uv":[15.75,14.5,16.0,14.75],"rotation":0,"texture":"#0","tintindex":0},"down":{"uv":[15.75,14.5,16.0,14.75],"rotation":0,"texture":"#0","tintindex":0}}},{"from":[9.857143,12.857143,7.428571],"to":[9.857143,15.142858,8.571428],"rotation":{"angle":22.5,"axis":"x","origin":[8.571428,13.142858,6.5714283]},"faces":{"east":{"uv":[15.75,14.5,16.0,14.75],"rotation":0,"texture":"#0","tintindex":0},"south":{"uv":[15.75,14.5,16.0,14.75],"rotation":0,"texture":"#0","tintindex":0},"north":{"uv":[15.75,14.5,16.0,14.75],"rotation":0,"texture":"#0","tintindex":0},"west":{"uv":[15.75,14.75,16.0,15.0],"rotation":0,"texture":"#0","tintindex":0},"up":{"uv":[15.75,14.5,16.0,14.75],"rotation":0,"texture":"#0","tintindex":0},"down":{"uv":[15.75,14.5,16.0,14.75],"rotation":0,"texture":"#0","tintindex":0}}},{"from":[9.857143,12.857143,6.285714],"to":[9.857143,15.714286,7.428571],"rotation":{"angle":22.5,"axis":"x","origin":[8.571428,13.142858,6.5714283]},"faces":{"east":{"uv":[15.75,14.5,16.0,14.75],"rotation":0,"texture":"#0","tintindex":0},"south":{"uv":[15.75,14.5,16.0,14.75],"rotation":0,"texture":"#0","tintindex":0},"north":{"uv":[15.75,14.5,16.0,14.75],"rotation":0,"texture":"#0","tintindex":0},"west":{"uv":[15.75,14.75,16.0,15.0],"rotation":0,"texture":"#0","tintindex":0},"up":{"uv":[15.75,14.5,16.0,14.75],"rotation":0,"texture":"#0","tintindex":0},"down":{"uv":[15.75,14.5,16.0,14.75],"rotation":0,"texture":"#0","tintindex":0}}},{"from":[9.571428,12.857143,7.428571],"to":[9.571428,15.142858,8.571428],"rotation":{"angle":22.5,"axis":"x","origin":[7.428571,13.142858,6.5714283]},"faces":{"east":{"uv":[16.0,14.75,15.75,15.0],"rotation":0,"texture":"#0","tintindex":0},"south":{"uv":[16.0,14.5,15.75,14.75],"rotation":0,"texture":"#0","tintindex":0},"north":{"uv":[16.0,14.5,15.75,14.75],"rotation":0,"texture":"#0","tintindex":0},"west":{"uv":[16.0,14.5,15.75,14.75],"rotation":0,"texture":"#0","tintindex":0},"up":{"uv":[16.0,14.5,15.75,14.75],"rotation":0,"texture":"#0","tintindex":0},"down":{"uv":[16.0,14.5,15.75,14.75],"rotation":0,"texture":"#0","tintindex":0}}},{"from":[9.571428,12.857143,6.285714],"to":[9.571428,15.714286,7.428571],"rotation":{"angle":22.5,"axis":"x","origin":[7.428571,13.142858,6.5714283]},"faces":{"east":{"uv":[16.0,14.75,15.75,15.0],"rotation":0,"texture":"#0","tintindex":0},"south":{"uv":[16.0,14.5,15.75,14.75],"rotation":0,"texture":"#0","tintindex":0},"north":{"uv":[16.0,14.5,15.75,14.75],"rotation":0,"texture":"#0","tintindex":0},"west":{"uv":[16.0,14.5,15.75,14.75],"rotation":0,"texture":"#0","tintindex":0},"up":{"uv":[16.0,14.5,15.75,14.75],"rotation":0,"texture":"#0","tintindex":0},"down":{"uv":[16.0,14.5,15.75,14.75],"rotation":0,"texture":"#0","tintindex":0}}},{"from":[9.714286,13.142858,6.5714283],"to":[9.714286,15.428572,8.285714],"rotation":{"angle":22.5,"axis":"x","origin":[7.428571,13.142858,6.5714283]},"faces":{"east":{"uv":[2.25,13.0,1.5,14.0],"rotation":0,"texture":"#0","tintindex":0},"south":{"uv":[0.0,0.0,0.0,1.0],"rotation":0,"texture":"#0","tintindex":0},"north":{"uv":[0.0,0.0,0.0,1.0],"rotation":0,"texture":"#0","tintindex":0},"west":{"uv":[1.5,13.0,2.25,14.0],"rotation":0,"texture":"#0","tintindex":0},"up":{"uv":[0.0,0.75,0.0,0.0],"rotation":0,"texture":"#0","tintindex":0},"down":{"uv":[0.0,0.0,0.0,0.75],"rotation":0,"texture":"#0","tintindex":0}}},{"from":[10.714286,8.857143,6.285714],"to":[10.714286,12.285715,7.428571],"rotation":{"angle":22.5,"axis":"y","origin":[10.571428,9.142858,6.0]},"faces":{"east":{"uv":[16.0,14.5,15.75,14.75],"rotation":0,"texture":"#0","tintindex":0},"south":{"uv":[16.0,14.5,15.75,14.75],"rotation":0,"texture":"#0","tintindex":0},"north":{"uv":[16.0,14.5,15.75,14.75],"rotation":0,"texture":"#0","tintindex":0},"west":{"uv":[16.0,14.75,15.75,15.0],"rotation":0,"texture":"#0","tintindex":0},"up":{"uv":[16.0,14.5,15.75,14.75],"rotation":0,"texture":"#0","tintindex":0},"down":{"uv":[16.0,14.5,15.75,14.75],"rotation":0,"texture":"#0","tintindex":0}}},{"from":[10.714286,9.428572,6.857143],"to":[10.714286,12.857143,8.0],"rotation":{"angle":22.5,"axis":"y","origin":[10.571428,9.142858,6.0]},"faces":{"east":{"uv":[16.0,14.5,15.75,14.75],"rotation":0,"texture":"#0","tintindex":0},"south":{"uv":[16.0,14.5,15.75,14.75],"rotation":0,"texture":"#0","tintindex":0},"north":{"uv":[16.0,14.5,15.75,14.75],"rotation":0,"texture":"#0","tintindex":0},"west":{"uv":[16.0,14.75,15.75,15.0],"rotation":0,"texture":"#0","tintindex":0},"up":{"uv":[16.0,14.5,15.75,14.75],"rotation":0,"texture":"#0","tintindex":0},"down":{"uv":[16.0,14.5,15.75,14.75],"rotation":0,"texture":"#0","tintindex":0}}},{"from":[10.714286,10.571428,7.428571],"to":[10.714286,12.857143,8.571428],"rotation":{"angle":22.5,"axis":"y","origin":[10.571428,9.142858,6.0]},"faces":{"east":{"uv":[16.0,14.5,15.75,14.75],"rotation":0,"texture":"#0","tintindex":0},"south":{"uv":[16.0,14.5,15.75,14.75],"rotation":0,"texture":"#0","tintindex":0},"north":{"uv":[16.0,14.5,15.75,14.75],"rotation":0,"texture":"#0","tintindex":0},"west":{"uv":[16.0,14.75,15.75,15.0],"rotation":0,"texture":"#0","tintindex":0},"up":{"uv":[16.0,14.5,15.75,14.75],"rotation":0,"texture":"#0","tintindex":0},"down":{"uv":[16.0,14.5,15.75,14.75],"rotation":0,"texture":"#0","tintindex":0}}},{"from":[10.714286,11.714286,8.571428],"to":[10.714286,14.0,9.714286],"rotation":{"angle":22.5,"axis":"y","origin":[10.571428,9.142858,6.0]},"faces":{"east":{"uv":[16.0,14.5,15.75,14.75],"rotation":0,"texture":"#0","tintindex":0},"south":{"uv":[16.0,14.5,15.75,14.75],"rotation":0,"texture":"#0","tintindex":0},"north":{"uv":[16.0,14.5,15.75,14.75],"rotation":0,"texture":"#0","tintindex":0},"west":{"uv":[16.0,14.75,15.75,15.0],"rotation":0,"texture":"#0","tintindex":0},"up":{"uv":[16.0,14.5,15.75,14.75],"rotation":0,"texture":"#0","tintindex":0},"down":{"uv":[16.0,14.5,15.75,14.75],"rotation":0,"texture":"#0","tintindex":0}}},{"from":[10.714286,11.142858,8.0],"to":[10.714286,13.428572,9.142858],"rotation":{"angle":22.5,"axis":"y","origin":[10.571428,9.142858,6.0]},"faces":{"east":{"uv":[16.0,14.5,15.75,14.75],"rotation":0,"texture":"#0","tintindex":0},"south":{"uv":[16.0,14.5,15.75,14.75],"rotation":0,"texture":"#0","tintindex":0},"north":{"uv":[16.0,14.5,15.75,14.75],"rotation":0,"texture":"#0","tintindex":0},"west":{"uv":[16.0,14.75,15.75,15.0],"rotation":0,"texture":"#0","tintindex":0},"up":{"uv":[16.0,14.5,15.75,14.75],"rotation":0,"texture":"#0","tintindex":0},"down":{"uv":[16.0,14.5,15.75,14.75],"rotation":0,"texture":"#0","tintindex":0}}},{"from":[10.714286,11.714286,9.142858],"to":[10.714286,14.571428,10.285714],"rotation":{"angle":22.5,"axis":"y","origin":[10.571428,9.142858,6.0]},"faces":{"east":{"uv":[16.0,14.5,15.75,14.75],"rotation":0,"texture":"#0","tintindex":0},"south":{"uv":[16.0,14.5,15.75,14.75],"rotation":0,"texture":"#0","tintindex":0},"north":{"uv":[16.0,14.5,15.75,14.75],"rotation":0,"texture":"#0","tintindex":0},"west":{"uv":[16.0,14.75,15.75,15.0],"rotation":0,"texture":"#0","tintindex":0},"up":{"uv":[16.0,14.5,15.75,14.75],"rotation":0,"texture":"#0","tintindex":0},"down":{"uv":[16.0,14.5,15.75,14.75],"rotation":0,"texture":"#0","tintindex":0}}},{"from":[10.514286,11.714286,9.142858],"to":[10.514286,14.571428,10.285714],"rotation":{"angle":22.5,"axis":"y","origin":[10.571428,9.142858,6.0]},"faces":{"east":{"uv":[16.0,14.75,15.75,15.0],"rotation":0,"texture":"#0","tintindex":0},"south":{"uv":[16.0,14.5,15.75,14.75],"rotation":0,"texture":"#0","tintindex":0},"north":{"uv":[16.0,14.5,15.75,14.75],"rotation":0,"texture":"#0","tintindex":0},"west":{"uv":[16.0,14.5,15.75,14.75],"rotation":0,"texture":"#0","tintindex":0},"up":{"uv":[16.0,14.5,15.75,14.75],"rotation":0,"texture":"#0","tintindex":0},"down":{"uv":[16.0,14.5,15.75,14.75],"rotation":0,"texture":"#0","tintindex":0}}},{"from":[10.514286,11.142858,8.0],"to":[10.514286,13.428572,9.142858],"rotation":{"angle":22.5,"axis":"y","origin":[10.571428,9.142858,6.0]},"faces":{"east":{"uv":[16.0,14.75,15.75,15.0],"rotation":0,"texture":"#0","tintindex":0},"south":{"uv":[16.0,14.5,15.75,14.75],"rotation":0,"texture":"#0","tintindex":0},"north":{"uv":[16.0,14.5,15.75,14.75],"rotation":0,"texture":"#0","tintindex":0},"west":{"uv":[16.0,14.5,15.75,14.75],"rotation":0,"texture":"#0","tintindex":0},"up":{"uv":[16.0,14.5,15.75,14.75],"rotation":0,"texture":"#0","tintindex":0},"down":{"uv":[16.0,14.5,15.75,14.75],"rotation":0,"texture":"#0","tintindex":0}}},{"from":[10.514286,11.714286,8.571428],"to":[10.514286,14.0,9.714286],"rotation":{"angle":22.5,"axis":"y","origin":[10.571428,9.142858,6.0]},"faces":{"east":{"uv":[16.0,14.75,15.75,15.0],"rotation":0,"texture":"#0","tintindex":0},"south":{"uv":[16.0,14.5,15.75,14.75],"rotation":0,"texture":"#0","tintindex":0},"north":{"uv":[16.0,14.5,15.75,14.75],"rotation":0,"texture":"#0","tintindex":0},"west":{"uv":[16.0,14.5,15.75,14.75],"rotation":0,"texture":"#0","tintindex":0},"up":{"uv":[16.0,14.5,15.75,14.75],"rotation":0,"texture":"#0","tintindex":0},"down":{"uv":[16.0,14.5,15.75,14.75],"rotation":0,"texture":"#0","tintindex":0}}},{"from":[10.514286,10.571428,7.428571],"to":[10.514286,12.857143,8.571428],"rotation":{"angle":22.5,"axis":"y","origin":[10.571428,9.142858,6.0]},"faces":{"east":{"uv":[16.0,14.75,15.75,15.0],"rotation":0,"texture":"#0","tintindex":0},"south":{"uv":[16.0,14.5,15.75,14.75],"rotation":0,"texture":"#0","tintindex":0},"north":{"uv":[16.0,14.5,15.75,14.75],"rotation":0,"texture":"#0","tintindex":0},"west":{"uv":[16.0,14.5,15.75,14.75],"rotation":0,"texture":"#0","tintindex":0},"up":{"uv":[16.0,14.5,15.75,14.75],"rotation":0,"texture":"#0","tintindex":0},"down":{"uv":[16.0,14.5,15.75,14.75],"rotation":0,"texture":"#0","tintindex":0}}},{"from":[10.514286,9.428572,6.857143],"to":[10.514286,12.857143,8.0],"rotation":{"angle":22.5,"axis":"y","origin":[10.571428,9.142858,6.0]},"faces":{"east":{"uv":[16.0,14.75,15.75,15.0],"rotation":0,"texture":"#0","tintindex":0},"south":{"uv":[16.0,14.5,15.75,14.75],"rotation":0,"texture":"#0","tintindex":0},"north":{"uv":[16.0,14.5,15.75,14.75],"rotation":0,"texture":"#0","tintindex":0},"west":{"uv":[16.0,14.5,15.75,14.75],"rotation":0,"texture":"#0","tintindex":0},"up":{"uv":[16.0,14.5,15.75,14.75],"rotation":0,"texture":"#0","tintindex":0},"down":{"uv":[16.0,14.5,15.75,14.75],"rotation":0,"texture":"#0","tintindex":0}}},{"from":[10.514286,8.857143,6.285714],"to":[10.514286,12.285715,7.428571],"rotation":{"angle":22.5,"axis":"y","origin":[10.571428,9.142858,6.0]},"faces":{"east":{"uv":[16.0,14.75,15.75,15.0],"rotation":0,"texture":"#0","tintindex":0},"south":{"uv":[16.0,14.5,15.75,14.75],"rotation":0,"texture":"#0","tintindex":0},"north":{"uv":[16.0,14.5,15.75,14.75],"rotation":0,"texture":"#0","tintindex":0},"west":{"uv":[16.0,14.5,15.75,14.75],"rotation":0,"texture":"#0","tintindex":0},"up":{"uv":[16.0,14.5,15.75,14.75],"rotation":0,"texture":"#0","tintindex":0},"down":{"uv":[16.0,14.5,15.75,14.75],"rotation":0,"texture":"#0","tintindex":0}}},{"from":[10.571428,9.142858,6.0],"to":[10.571428,14.285715,10.0],"rotation":{"angle":22.5,"axis":"y","origin":[10.571428,9.142858,6.0]},"faces":{"east":{"uv":[9.0,3.5,10.75,5.75],"rotation":0,"texture":"#0","tintindex":0},"south":{"uv":[0.0,0.0,0.0,2.25],"rotation":0,"texture":"#0","tintindex":0},"north":{"uv":[0.0,0.0,0.0,2.25],"rotation":0,"texture":"#0","tintindex":0},"west":{"uv":[10.75,3.5,9.0,5.75],"rotation":0,"texture":"#0","tintindex":0},"up":{"uv":[0.0,1.75,0.0,0.0],"rotation":0,"texture":"#0","tintindex":0},"down":{"uv":[0.0,0.0,0.0,1.75],"rotation":0,"texture":"#0","tintindex":0}}}],"textures":{"0":"modelengine:entity/possessed_cinder_armor"},"display":{"head":{"translation":[0.0,-6.4,0.0],"scale":[4.0,4.0,4.0]}}}